reposcope/__init__.py
reposcope/src/__init__.py
reposcope/src/ai/__init__.py
reposcope/src/ai/factory.py
reposcope/src/ai/noop.py
reposcope/src/ai/openai_provider.py
reposcope/src/ai/provider.py
reposcope/src/analyzers/__init__.py
reposcope/src/analyzers/architecture.py
reposcope/src/analyzers/onboarding.py
reposcope/src/analyzers/risks.py
reposcope/src/cli/__init__.py
reposcope/src/cli/main.py
reposcope/src/report/__init__.py
reposcope/src/report/pr_comment.py
reposcope/src/report/writer.py
reposcope/src/scanner/__init__.py
reposcope/src/scanner/repo_loader.py
reposcope/src/scanner/repo_scanner.py
reposcope/src/scanner/types.py
reposcope/src/utils/__init__.py
reposcope/src/utils/git_tools.py
reposcope/src/utils/ignore.py
reposcope/src/utils/paths.py
reposcope_ai-0.10.0.dist-info/METADATA
reposcope_ai-0.10.0.dist-info/WHEEL
reposcope_ai-0.10.0.dist-info/entry_points.txt
reposcope_ai-0.10.0.dist-info/licenses/LICENSE
reposcope_ai-0.10.0.dist-info/RECORD
