Metadata-Version: 2.4
Name: reposcope-ai
Version: 0.10.0
Summary: Deterministic CLI that audits a Git repository and generates actionable documentation
Project-URL: Homepage, https://github.com/Siggmond/reposcope-ai
Project-URL: Repository, https://github.com/Siggmond/reposcope-ai
Project-URL: Issues, https://github.com/Siggmond/reposcope-ai/issues
Author: RepoScope AI
License: MIT License
License-File: LICENSE
Keywords: analysis,cli,code-review,developer-tools,github,onboarding,repo-audit,repository
Classifier: Development Status :: 4 - Beta
Classifier: Intended Audience :: Developers
Classifier: License :: OSI Approved :: MIT License
Classifier: Programming Language :: Python :: 3 :: Only
Classifier: Programming Language :: Python :: 3.9
Classifier: Programming Language :: Python :: 3.10
Classifier: Programming Language :: Python :: 3.11
Classifier: Programming Language :: Python :: 3.12
Classifier: Topic :: Software Development :: Documentation
Classifier: Topic :: Software Development :: Quality Assurance
Requires-Python: >=3.9
Requires-Dist: rich>=13.0.0
Requires-Dist: typer>=0.9.0
Provides-Extra: dev
Requires-Dist: pytest>=7.0.0; extra == 'dev'
